safai/__init__.py
safai/config.py
safai/main.py
safai/pipeline.py
safai/directory_handler/__init__.py
safai/directory_handler/handler.py
safai/model_proxy/__init__.py
safai/model_proxy/claude.py
safai/model_proxy/gemini.py
safai/model_proxy/model_proxy.py
safai/model_proxy/openai.py
safai/model_proxy/shared.py
safai-0.4.4.dist-info/licenses/LICENSE
safai-0.4.4.dist-info/METADATA
safai-0.4.4.dist-info/WHEEL
safai-0.4.4.dist-info/entry_points.txt
safai-0.4.4.dist-info/top_level.txt
safai-0.4.4.dist-info/RECORD
