Metadata-Version: 2.4
Name: safai
Version: 0.4.4
Summary: CLI that cleans up folder by intelligently organizing it
Author-email: Shubham Biswas <connect@xolve.dev>
License: GPL-3.0-or-later
Requires-Python: >=3.10
License-File: LICENSE
Requires-Dist: anthropic>=0.57.1
Requires-Dist: google-genai>=1.24.0
Requires-Dist: openai>=1.93.2
Requires-Dist: pydantic>=2.11.7
Requires-Dist: pyyaml>=6.0.2
Requires-Dist: rich>=14.0.0
Requires-Dist: typer>=0.16.0
Dynamic: license-file
